[
  {
    "threadId": 32556,
    "threadName": "RequestProcessorAsyncPool-32556",
    "operationStack": [
      {
        "startTime": 1516572000003,
        "subsystem": "Model Query Task",
        "synchronic": true,
        "id": "4f831351157e471cb52de05c18adca7f",
        "message": "General CMDB request",
        "operationName": "Model Query: Get Objects By Condition: class name:sap_transport is_derived:true properties:(root_las",
        "customerID": {
          "_customerID": 1,
          "_customerName": "Default Client"
        },
        "callerApplication": "CMDB"
      },
      {
        "startTime": 1516572000003,
        "subsystem": "Tql Calculator Task",
        "synchronic": true,
        "id": "430601a4ae192e949d09b11fda0dbd1d",
        "message": "General CMDB request",
        "operationName": "Model Calculate Pattern:SAP_Old_Transports1516572000002",
        "customerID": {
          "_customerID": 1,
          "_customerName": "Default Client"
        },
        "callerApplication": "CMDB"
      },
      {
        "startTime": 1516572000003,
        "subsystem": "Tql Pattern Calc Process Task",
        "synchronic": true,
        "id": "4d250f11281f564b806a06f3bf94c987",
        "message": "General CMDB request",
        "operationName": "Tql Command: Process AdHoc Calculate",
        "customerID": {
          "_customerID": 1,
          "_customerName": "Default Client"
        },
        "callerApplication": "CMDB"
      },
      {
        "startTime": 1516572000003,
        "subsystem": "Tql Results Utils Task",
        "synchronic": true,
        "id": "42a207f272f31c04af3cc88fd38d61b2",
        "message": "General CMDB request",
        "operationName": "Tql Query: Get Ad Hoc Server Tql Result (By Pattern ID). Pattern [SAP_Old_Transports1516572000002]",
        "customerID": {
          "_customerID": 1,
          "_customerName": "Default Client"
        },
        "callerApplication": "CMDB"
      },
      {
        "startTime": 1516572000002,
        "subsystem": "Tql Results Utils Task",
        "synchronic": true,
        "id": "41eeab7e68ba5d09940b8a7cb2428a2f",
        "message": "General CMDB request",
        "operationName": "Tql Update: Add Pattern To Result Repository. Pattern [SAP_Old_Transports1516572000002] DecayTimeMS ",
        "customerID": {
          "_customerID": 1,
          "_customerName": "Default Client"
        },
        "callerApplication": "CMDB"
      },
      {
        "startTime": 1516572000002,
        "subsystem": "Enrichment Ad Hoc Calculator Task",
        "synchronic": false,
        "id": "428919d2921ce65aa2638153ab706005",
        "message": "General CMDB request",
        "operationName": "Enrichment Command: Calculate enrichment{EnrichmentName\u003dSAP_Old_Transports}",
        "customerID": {
          "_customerID": 1,
          "_customerName": "Default Client"
        },
        "callerApplication": "CMDB"
      }
    ]
  }
]